[{
  "_id": {
    "$oid": "6835841003d7a3a01f83ea2d"
  },
  "userId": {
    "$oid": "6835826003d7a3a01f83ea22"
  },
  "age": 18,
  "sex": "male",
  "weight": 34,
  "height": 344,
  "bloodType": "A+",
  "allergies": [],
  "chronicConditions": [
    "mental_health",
    "autoimmune"
  ],
  "medications": [],
  "familyHistory": [],
  "dataShareConsent": false,
  "preferredLanguage": "en",
  "located": "karachi",
  "ethnicity": "asian",
  "birthplace": "karachi",
  "diet": "vegetarian",
  "lastUpdated": {
    "$date": "2025-05-27T12:34:00.740Z"
  },
  "__v": 0
},
{
  "_id": {
    "$oid": "683816f22626711e969b7ddf"
  },
  "userId": {
    "$oid": "683815b10214394db446fdb3"
  },
  "age": 30,
  "sex": "male",
  "weight": 42,
  "height": 123,
  "bloodType": "AB-",
  "allergies": [],
  "chronicConditions": [
    "mental_health",
    "autoimmune"
  ],
  "medications": [],
  "familyHistory": [],
  "dataShareConsent": false,
  "preferredLanguage": "en",
  "located": "karachi",
  "ethnicity": "hispanic",
  "birthplace": "pakistan",
  "diet": "pescatarian",
  "lastUpdated": {
    "$date": "2025-05-29T08:12:34.804Z"
  },
  "__v": 0
}]